{"extent":[808357.5,824117.5,841357.5,845117.5],"grids":[{"id":0,"height":111,"xMinPercent":[0,1],"yMinPercent":[0,1],"xMaxPercent":[1,11],"yMaxPercent":[1,7]},{"id":1,"height":66666,"xMinPercent":[1,11],"yMinPercent":[0,1],"xMaxPercent":[2,11],"yMaxPercent":[1,7]},{"id":2,"height":-9999,"xMinPercent":[2,11],"yMinPercent":[0,1],"xMaxPercent":[3,11],"yMaxPercent":[1,7]},{"id":3,"height":-9999,"xMinPercent":[3,11],"yMinPercent":[0,1],"xMaxPercent":[4,11],"yMaxPercent":[1,7]},{"id":4,"height":-9999,"xMinPercent":[4,11],"yMinPercent":[0,1],"xMaxPercent":[5,11],"yMaxPercent":[1,7]},{"id":5,"height":-9999,"xMinPercent":[5,11],"yMinPercent":[0,1],"xMaxPercent":[6,11],"yMaxPercent":[1,7]},{"id":6,"height":-9999,"xMinPercent":[6,11],"yMinPercent":[0,1],"xMaxPercent":[7,11],"yMaxPercent":[1,7]},{"id":7,"height":-9999,"xMinPercent":[7,11],"yMinPercent":[0,1],"xMaxPercent":[8,11],"yMaxPercent":[1,7]},{"id":8,"height":-9999,"xMinPercent":[8,11],"yMinPercent":[0,1],"xMaxPercent":[9,11],"yMaxPercent":[1,7]},{"id":9,"height":-9999,"xMinPercent":[9,11],"yMinPercent":[0,1],"xMaxPercent":[10,11],"yMaxPercent":[1,7]},{"id":10,"height":-9999,"xMinPercent":[10,11],"yMinPercent":[0,1],"xMaxPercent":[1,1],"yMaxPercent":[1,7]},{"id":11,"height":-9999,"xMinPercent":[0,1],"yMinPercent":[1,7],"xMaxPercent":[1,11],"yMaxPercent":[2,7]},{"id":12,"height":-9999,"xMinPercent":[1,11],"yMinPercent":[1,7],"xMaxPercent":[2,11],"yMaxPercent":[2,7]},{"id":13,"height":-9999,"xMinPercent":[2,11],"yMinPercent":[1,7],"xMaxPercent":[3,11],"yMaxPercent":[2,7]},{"id":14,"height":-9999,"xMinPercent":[3,11],"yMinPercent":[1,7],"xMaxPercent":[4,11],"yMaxPercent":[2,7]},{"id":15,"height":-9999,"xMinPercent":[4,11],"yMinPercent":[1,7],"xMaxPercent":[5,11],"yMaxPercent":[2,7]},{"id":16,"height":-9999,"xMinPercent":[5,11],"yMinPercent":[1,7],"xMaxPercent":[6,11],"yMaxPercent":[2,7]},{"id":17,"height":-9999,"xMinPercent":[6,11],"yMinPercent":[1,7],"xMaxPercent":[7,11],"yMaxPercent":[2,7]},{"id":18,"height":-9999,"xMinPercent":[7,11],"yMinPercent":[1,7],"xMaxPercent":[8,11],"yMaxPercent":[2,7]},{"id":19,"height":-9999,"xMinPercent":[8,11],"yMinPercent":[1,7],"xMaxPercent":[9,11],"yMaxPercent":[2,7]},{"id":20,"height":-9999,"xMinPercent":[9,11],"yMinPercent":[1,7],"xMaxPercent":[10,11],"yMaxPercent":[2,7]},{"id":21,"height":-9999,"xMinPercent":[10,11],"yMinPercent":[1,7],"xMaxPercent":[1,1],"yMaxPercent":[2,7]},{"id":22,"height":-9999,"xMinPercent":[0,1],"yMinPercent":[2,7],"xMaxPercent":[1,11],"yMaxPercent":[3,7]},{"id":23,"height":-9999,"xMinPercent":[1,11],"yMinPercent":[2,7],"xMaxPercent":[2,11],"yMaxPercent":[3,7]},{"id":24,"height":-9999,"xMinPercent":[2,11],"yMinPercent":[2,7],"xMaxPercent":[3,11],"yMaxPercent":[3,7]},{"id":25,"height":-9999,"xMinPercent":[3,11],"yMinPercent":[2,7],"xMaxPercent":[4,11],"yMaxPercent":[3,7]},{"id":26,"height":-9999,"xMinPercent":[4,11],"yMinPercent":[2,7],"xMaxPercent":[5,11],"yMaxPercent":[3,7]},{"id":27,"height":-9999,"xMinPercent":[5,11],"yMinPercent":[2,7],"xMaxPercent":[6,11],"yMaxPercent":[3,7]},{"id":28,"height":-9999,"xMinPercent":[6,11],"yMinPercent":[2,7],"xMaxPercent":[7,11],"yMaxPercent":[3,7]},{"id":29,"height":-9999,"xMinPercent":[7,11],"yMinPercent":[2,7],"xMaxPercent":[8,11],"yMaxPercent":[3,7]},{"id":30,"height":-9999,"xMinPercent":[8,11],"yMinPercent":[2,7],"xMaxPercent":[9,11],"yMaxPercent":[3,7]},{"id":31,"height":-9999,"xMinPercent":[9,11],"yMinPercent":[2,7],"xMaxPercent":[10,11],"yMaxPercent":[3,7]},{"id":32,"height":-9999,"xMinPercent":[10,11],"yMinPercent":[2,7],"xMaxPercent":[1,1],"yMaxPercent":[3,7]},{"id":33,"height":-9999,"xMinPercent":[0,1],"yMinPercent":[3,7],"xMaxPercent":[1,11],"yMaxPercent":[4,7]},{"id":34,"height":-9999,"xMinPercent":[1,11],"yMinPercent":[3,7],"xMaxPercent":[2,11],"yMaxPercent":[4,7]},{"id":35,"height":-9999,"xMinPercent":[2,11],"yMinPercent":[3,7],"xMaxPercent":[3,11],"yMaxPercent":[4,7]},{"id":36,"height":-9999,"xMinPercent":[3,11],"yMinPercent":[3,7],"xMaxPercent":[4,11],"yMaxPercent":[4,7]},{"id":37,"height":-9999,"xMinPercent":[4,11],"yMinPercent":[3,7],"xMaxPercent":[5,11],"yMaxPercent":[4,7]},{"id":38,"height":-9999,"xMinPercent":[5,11],"yMinPercent":[3,7],"xMaxPercent":[6,11],"yMaxPercent":[4,7]},{"id":39,"height":-9999,"xMinPercent":[6,11],"yMinPercent":[3,7],"xMaxPercent":[7,11],"yMaxPercent":[4,7]},{"id":40,"height":-9999,"xMinPercent":[7,11],"yMinPercent":[3,7],"xMaxPercent":[8,11],"yMaxPercent":[4,7]},{"id":41,"height":-9999,"xMinPercent":[8,11],"yMinPercent":[3,7],"xMaxPercent":[9,11],"yMaxPercent":[4,7]},{"id":42,"height":-9999,"xMinPercent":[9,11],"yMinPercent":[3,7],"xMaxPercent":[10,11],"yMaxPercent":[4,7]},{"id":43,"height":-9999,"xMinPercent":[10,11],"yMinPercent":[3,7],"xMaxPercent":[1,1],"yMaxPercent":[4,7]},{"id":44,"height":-9999,"xMinPercent":[0,1],"yMinPercent":[4,7],"xMaxPercent":[1,11],"yMaxPercent":[5,7]},{"id":45,"height":-9999,"xMinPercent":[1,11],"yMinPercent":[4,7],"xMaxPercent":[2,11],"yMaxPercent":[5,7]},{"id":46,"height":-9999,"xMinPercent":[2,11],"yMinPercent":[4,7],"xMaxPercent":[3,11],"yMaxPercent":[5,7]},{"id":47,"height":-9999,"xMinPercent":[3,11],"yMinPercent":[4,7],"xMaxPercent":[4,11],"yMaxPercent":[5,7]},{"id":48,"height":-9999,"xMinPercent":[4,11],"yMinPercent":[4,7],"xMaxPercent":[5,11],"yMaxPercent":[5,7]},{"id":49,"height":-9999,"xMinPercent":[5,11],"yMinPercent":[4,7],"xMaxPercent":[6,11],"yMaxPercent":[5,7]},{"id":50,"height":-9999,"xMinPercent":[6,11],"yMinPercent":[4,7],"xMaxPercent":[7,11],"yMaxPercent":[5,7]},{"id":51,"height":-9999,"xMinPercent":[7,11],"yMinPercent":[4,7],"xMaxPercent":[8,11],"yMaxPercent":[5,7]},{"id":52,"height":-9999,"xMinPercent":[8,11],"yMinPercent":[4,7],"xMaxPercent":[9,11],"yMaxPercent":[5,7]},{"id":53,"height":-9999,"xMinPercent":[9,11],"yMinPercent":[4,7],"xMaxPercent":[10,11],"yMaxPercent":[5,7]},{"id":54,"height":-9999,"xMinPercent":[10,11],"yMinPercent":[4,7],"xMaxPercent":[1,1],"yMaxPercent":[5,7]},{"id":55,"height":-9999,"xMinPercent":[0,1],"yMinPercent":[5,7],"xMaxPercent":[1,11],"yMaxPercent":[6,7]},{"id":56,"height":-9999,"xMinPercent":[1,11],"yMinPercent":[5,7],"xMaxPercent":[2,11],"yMaxPercent":[6,7]},{"id":57,"height":-9999,"xMinPercent":[2,11],"yMinPercent":[5,7],"xMaxPercent":[3,11],"yMaxPercent":[6,7]},{"id":58,"height":-9999,"xMinPercent":[3,11],"yMinPercent":[5,7],"xMaxPercent":[4,11],"yMaxPercent":[6,7]},{"id":59,"height":-9999,"xMinPercent":[4,11],"yMinPercent":[5,7],"xMaxPercent":[5,11],"yMaxPercent":[6,7]},{"id":60,"height":-9999,"xMinPercent":[5,11],"yMinPercent":[5,7],"xMaxPercent":[6,11],"yMaxPercent":[6,7]},{"id":61,"height":-9999,"xMinPercent":[6,11],"yMinPercent":[5,7],"xMaxPercent":[7,11],"yMaxPercent":[6,7]},{"id":62,"height":-9999,"xMinPercent":[7,11],"yMinPercent":[5,7],"xMaxPercent":[8,11],"yMaxPercent":[6,7]},{"id":63,"height":-9999,"xMinPercent":[8,11],"yMinPercent":[5,7],"xMaxPercent":[9,11],"yMaxPercent":[6,7]},{"id":64,"height":-9999,"xMinPercent":[9,11],"yMinPercent":[5,7],"xMaxPercent":[10,11],"yMaxPercent":[6,7]},{"id":65,"height":-9999,"xMinPercent":[10,11],"yMinPercent":[5,7],"xMaxPercent":[1,1],"yMaxPercent":[6,7]},{"id":66,"height":-9999,"xMinPercent":[0,1],"yMinPercent":[6,7],"xMaxPercent":[1,11],"yMaxPercent":[1,1]},{"id":67,"height":-9999,"xMinPercent":[1,11],"yMinPercent":[6,7],"xMaxPercent":[2,11],"yMaxPercent":[1,1]},{"id":68,"height":-9999,"xMinPercent":[2,11],"yMinPercent":[6,7],"xMaxPercent":[3,11],"yMaxPercent":[1,1]},{"id":69,"height":-9999,"xMinPercent":[3,11],"yMinPercent":[6,7],"xMaxPercent":[4,11],"yMaxPercent":[1,1]},{"id":70,"height":-9999,"xMinPercent":[4,11],"yMinPercent":[6,7],"xMaxPercent":[5,11],"yMaxPercent":[1,1]},{"id":71,"height":-9999,"xMinPercent":[5,11],"yMinPercent":[6,7],"xMaxPercent":[6,11],"yMaxPercent":[1,1]},{"id":72,"height":-9999,"xMinPercent":[6,11],"yMinPercent":[6,7],"xMaxPercent":[7,11],"yMaxPercent":[1,1]},{"id":73,"height":-9999,"xMinPercent":[7,11],"yMinPercent":[6,7],"xMaxPercent":[8,11],"yMaxPercent":[1,1]},{"id":74,"height":-9999,"xMinPercent":[8,11],"yMinPercent":[6,7],"xMaxPercent":[9,11],"yMaxPercent":[1,1]},{"id":75,"height":-9999,"xMinPercent":[9,11],"yMinPercent":[6,7],"xMaxPercent":[10,11],"yMaxPercent":[1,1]},{"id":76,"height":-9999,"xMinPercent":[10,11],"yMinPercent":[6,7],"xMaxPercent":[1,1],"yMaxPercent":[1,1]}],"edges":[{"id":0,"adjGrids":[0,11],"minPercent":[0,1],"maxPercent":[1,11],"height":222,"edgeCode":0},{"id":1,"adjGrids":[0,null],"minPercent":[0,1],"maxPercent":[1,7],"height":333,"edgeCode":1},{"id":2,"adjGrids":[0,null],"minPercent":[0,1],"maxPercent":[1,11],"height":444,"edgeCode":2},{"id":3,"adjGrids":[0,1],"minPercent":[0,1],"maxPercent":[1,7],"height":555,"edgeCode":3},{"id":4,"adjGrids":[1,12],"minPercent":[1,11],"maxPercent":[2,11],"height":-9999,"edgeCode":0},{"id":5,"adjGrids":[1,null],"minPercent":[1,11],"maxPercent":[2,11],"height":-9999,"edgeCode":2},{"id":6,"adjGrids":[1,2],"minPercent":[0,1],"maxPercent":[1,7],"height":-9999,"edgeCode":3},{"id":7,"adjGrids":[2,13],"minPercent":[2,11],"maxPercent":[3,11],"height":-9999,"edgeCode":0},{"id":8,"adjGrids":[2,null],"minPercent":[2,11],"maxPercent":[3,11],"height":-9999,"edgeCode":2},{"id":9,"adjGrids":[2,3],"minPercent":[0,1],"maxPercent":[1,7],"height":-9999,"edgeCode":3},{"id":10,"adjGrids":[3,14],"minPercent":[3,11],"maxPercent":[4,11],"height":-9999,"edgeCode":0},{"id":11,"adjGrids":[3,null],"minPercent":[3,11],"maxPercent":[4,11],"height":-9999,"edgeCode":2},{"id":12,"adjGrids":[3,4],"minPercent":[0,1],"maxPercent":[1,7],"height":-9999,"edgeCode":3},{"id":13,"adjGrids":[4,15],"minPercent":[4,11],"maxPercent":[5,11],"height":-9999,"edgeCode":0},{"id":14,"adjGrids":[4,null],"minPercent":[4,11],"maxPercent":[5,11],"height":-9999,"edgeCode":2},{"id":15,"adjGrids":[4,5],"minPercent":[0,1],"maxPercent":[1,7],"height":-9999,"edgeCode":3},{"id":16,"adjGrids":[5,16],"minPercent":[5,11],"maxPercent":[6,11],"height":-9999,"edgeCode":0},{"id":17,"adjGrids":[5,null],"minPercent":[5,11],"maxPercent":[6,11],"height":-9999,"edgeCode":2},{"id":18,"adjGrids":[5,6],"minPercent":[0,1],"maxPercent":[1,7],"height":-9999,"edgeCode":3},{"id":19,"adjGrids":[6,17],"minPercent":[6,11],"maxPercent":[7,11],"height":-9999,"edgeCode":0},{"id":20,"adjGrids":[6,null],"minPercent":[6,11],"maxPercent":[7,11],"height":-9999,"edgeCode":2},{"id":21,"adjGrids":[6,7],"minPercent":[0,1],"maxPercent":[1,7],"height":-9999,"edgeCode":3},{"id":22,"adjGrids":[7,18],"minPercent":[7,11],"maxPercent":[8,11],"height":-9999,"edgeCode":0},{"id":23,"adjGrids":[7,null],"minPercent":[7,11],"maxPercent":[8,11],"height":-9999,"edgeCode":2},{"id":24,"adjGrids":[7,8],"minPercent":[0,1],"maxPercent":[1,7],"height":-9999,"edgeCode":3},{"id":25,"adjGrids":[8,19],"minPercent":[8,11],"maxPercent":[9,11],"height":-9999,"edgeCode":0},{"id":26,"adjGrids":[8,null],"minPercent":[8,11],"maxPercent":[9,11],"height":-9999,"edgeCode":2},{"id":27,"adjGrids":[8,9],"minPercent":[0,1],"maxPercent":[1,7],"height":-9999,"edgeCode":3},{"id":28,"adjGrids":[9,20],"minPercent":[9,11],"maxPercent":[10,11],"height":-9999,"edgeCode":0},{"id":29,"adjGrids":[9,null],"minPercent":[9,11],"maxPercent":[10,11],"height":-9999,"edgeCode":2},{"id":30,"adjGrids":[9,10],"minPercent":[0,1],"maxPercent":[1,7],"height":-9999,"edgeCode":3},{"id":31,"adjGrids":[10,21],"minPercent":[10,11],"maxPercent":[1,1],"height":-9999,"edgeCode":0},{"id":32,"adjGrids":[10,null],"minPercent":[10,11],"maxPercent":[1,1],"height":-9999,"edgeCode":2},{"id":33,"adjGrids":[10,null],"minPercent":[0,1],"maxPercent":[1,7],"height":-9999,"edgeCode":3},{"id":34,"adjGrids":[11,22],"minPercent":[0,1],"maxPercent":[1,11],"height":-9999,"edgeCode":0},{"id":35,"adjGrids":[11,null],"minPercent":[1,7],"maxPercent":[2,7],"height":-9999,"edgeCode":1},{"id":36,"adjGrids":[11,12],"minPercent":[1,7],"maxPercent":[2,7],"height":-9999,"edgeCode":3},{"id":37,"adjGrids":[12,23],"minPercent":[1,11],"maxPercent":[2,11],"height":-9999,"edgeCode":0},{"id":38,"adjGrids":[12,13],"minPercent":[1,7],"maxPercent":[2,7],"height":-9999,"edgeCode":3},{"id":39,"adjGrids":[13,24],"minPercent":[2,11],"maxPercent":[3,11],"height":-9999,"edgeCode":0},{"id":40,"adjGrids":[13,14],"minPercent":[1,7],"maxPercent":[2,7],"height":-9999,"edgeCode":3},{"id":41,"adjGrids":[14,25],"minPercent":[3,11],"maxPercent":[4,11],"height":-9999,"edgeCode":0},{"id":42,"adjGrids":[14,15],"minPercent":[1,7],"maxPercent":[2,7],"height":-9999,"edgeCode":3},{"id":43,"adjGrids":[15,26],"minPercent":[4,11],"maxPercent":[5,11],"height":-9999,"edgeCode":0},{"id":44,"adjGrids":[15,16],"minPercent":[1,7],"maxPercent":[2,7],"height":-9999,"edgeCode":3},{"id":45,"adjGrids":[16,27],"minPercent":[5,11],"maxPercent":[6,11],"height":-9999,"edgeCode":0},{"id":46,"adjGrids":[16,17],"minPercent":[1,7],"maxPercent":[2,7],"height":-9999,"edgeCode":3},{"id":47,"adjGrids":[17,28],"minPercent":[6,11],"maxPercent":[7,11],"height":-9999,"edgeCode":0},{"id":48,"adjGrids":[17,18],"minPercent":[1,7],"maxPercent":[2,7],"height":-9999,"edgeCode":3},{"id":49,"adjGrids":[18,29],"minPercent":[7,11],"maxPercent":[8,11],"height":-9999,"edgeCode":0},{"id":50,"adjGrids":[18,19],"minPercent":[1,7],"maxPercent":[2,7],"height":-9999,"edgeCode":3},{"id":51,"adjGrids":[19,30],"minPercent":[8,11],"maxPercent":[9,11],"height":-9999,"edgeCode":0},{"id":52,"adjGrids":[19,20],"minPercent":[1,7],"maxPercent":[2,7],"height":-9999,"edgeCode":3},{"id":53,"adjGrids":[20,31],"minPercent":[9,11],"maxPercent":[10,11],"height":-9999,"edgeCode":0},{"id":54,"adjGrids":[20,21],"minPercent":[1,7],"maxPercent":[2,7],"height":-9999,"edgeCode":3},{"id":55,"adjGrids":[21,32],"minPercent":[10,11],"maxPercent":[1,1],"height":-9999,"edgeCode":0},{"id":56,"adjGrids":[21,null],"minPercent":[1,7],"maxPercent":[2,7],"height":-9999,"edgeCode":3},{"id":57,"adjGrids":[22,33],"minPercent":[0,1],"maxPercent":[1,11],"height":-9999,"edgeCode":0},{"id":58,"adjGrids":[22,null],"minPercent":[2,7],"maxPercent":[3,7],"height":-9999,"edgeCode":1},{"id":59,"adjGrids":[22,23],"minPercent":[2,7],"maxPercent":[3,7],"height":-9999,"edgeCode":3},{"id":60,"adjGrids":[23,34],"minPercent":[1,11],"maxPercent":[2,11],"height":-9999,"edgeCode":0},{"id":61,"adjGrids":[23,24],"minPercent":[2,7],"maxPercent":[3,7],"height":-9999,"edgeCode":3},{"id":62,"adjGrids":[24,35],"minPercent":[2,11],"maxPercent":[3,11],"height":-9999,"edgeCode":0},{"id":63,"adjGrids":[24,25],"minPercent":[2,7],"maxPercent":[3,7],"height":-9999,"edgeCode":3},{"id":64,"adjGrids":[25,36],"minPercent":[3,11],"maxPercent":[4,11],"height":-9999,"edgeCode":0},{"id":65,"adjGrids":[25,26],"minPercent":[2,7],"maxPercent":[3,7],"height":-9999,"edgeCode":3},{"id":66,"adjGrids":[26,37],"minPercent":[4,11],"maxPercent":[5,11],"height":-9999,"edgeCode":0},{"id":67,"adjGrids":[26,27],"minPercent":[2,7],"maxPercent":[3,7],"height":-9999,"edgeCode":3},{"id":68,"adjGrids":[27,38],"minPercent":[5,11],"maxPercent":[6,11],"height":-9999,"edgeCode":0},{"id":69,"adjGrids":[27,28],"minPercent":[2,7],"maxPercent":[3,7],"height":-9999,"edgeCode":3},{"id":70,"adjGrids":[28,39],"minPercent":[6,11],"maxPercent":[7,11],"height":-9999,"edgeCode":0},{"id":71,"adjGrids":[28,29],"minPercent":[2,7],"maxPercent":[3,7],"height":-9999,"edgeCode":3},{"id":72,"adjGrids":[29,40],"minPercent":[7,11],"maxPercent":[8,11],"height":-9999,"edgeCode":0},{"id":73,"adjGrids":[29,30],"minPercent":[2,7],"maxPercent":[3,7],"height":-9999,"edgeCode":3},{"id":74,"adjGrids":[30,41],"minPercent":[8,11],"maxPercent":[9,11],"height":-9999,"edgeCode":0},{"id":75,"adjGrids":[30,31],"minPercent":[2,7],"maxPercent":[3,7],"height":-9999,"edgeCode":3},{"id":76,"adjGrids":[31,42],"minPercent":[9,11],"maxPercent":[10,11],"height":-9999,"edgeCode":0},{"id":77,"adjGrids":[31,32],"minPercent":[2,7],"maxPercent":[3,7],"height":-9999,"edgeCode":3},{"id":78,"adjGrids":[32,43],"minPercent":[10,11],"maxPercent":[1,1],"height":-9999,"edgeCode":0},{"id":79,"adjGrids":[32,null],"minPercent":[2,7],"maxPercent":[3,7],"height":-9999,"edgeCode":3},{"id":80,"adjGrids":[33,44],"minPercent":[0,1],"maxPercent":[1,11],"height":-9999,"edgeCode":0},{"id":81,"adjGrids":[33,null],"minPercent":[3,7],"maxPercent":[4,7],"height":-9999,"edgeCode":1},{"id":82,"adjGrids":[33,34],"minPercent":[3,7],"maxPercent":[4,7],"height":-9999,"edgeCode":3},{"id":83,"adjGrids":[34,45],"minPercent":[1,11],"maxPercent":[2,11],"height":-9999,"edgeCode":0},{"id":84,"adjGrids":[34,35],"minPercent":[3,7],"maxPercent":[4,7],"height":-9999,"edgeCode":3},{"id":85,"adjGrids":[35,46],"minPercent":[2,11],"maxPercent":[3,11],"height":-9999,"edgeCode":0},{"id":86,"adjGrids":[35,36],"minPercent":[3,7],"maxPercent":[4,7],"height":-9999,"edgeCode":3},{"id":87,"adjGrids":[36,47],"minPercent":[3,11],"maxPercent":[4,11],"height":-9999,"edgeCode":0},{"id":88,"adjGrids":[36,37],"minPercent":[3,7],"maxPercent":[4,7],"height":-9999,"edgeCode":3},{"id":89,"adjGrids":[37,48],"minPercent":[4,11],"maxPercent":[5,11],"height":-9999,"edgeCode":0},{"id":90,"adjGrids":[37,38],"minPercent":[3,7],"maxPercent":[4,7],"height":-9999,"edgeCode":3},{"id":91,"adjGrids":[38,49],"minPercent":[5,11],"maxPercent":[6,11],"height":-9999,"edgeCode":0},{"id":92,"adjGrids":[38,39],"minPercent":[3,7],"maxPercent":[4,7],"height":-9999,"edgeCode":3},{"id":93,"adjGrids":[39,50],"minPercent":[6,11],"maxPercent":[7,11],"height":-9999,"edgeCode":0},{"id":94,"adjGrids":[39,40],"minPercent":[3,7],"maxPercent":[4,7],"height":-9999,"edgeCode":3},{"id":95,"adjGrids":[40,51],"minPercent":[7,11],"maxPercent":[8,11],"height":-9999,"edgeCode":0},{"id":96,"adjGrids":[40,41],"minPercent":[3,7],"maxPercent":[4,7],"height":-9999,"edgeCode":3},{"id":97,"adjGrids":[41,52],"minPercent":[8,11],"maxPercent":[9,11],"height":-9999,"edgeCode":0},{"id":98,"adjGrids":[41,42],"minPercent":[3,7],"maxPercent":[4,7],"height":-9999,"edgeCode":3},{"id":99,"adjGrids":[42,53],"minPercent":[9,11],"maxPercent":[10,11],"height":-9999,"edgeCode":0},{"id":100,"adjGrids":[42,43],"minPercent":[3,7],"maxPercent":[4,7],"height":-9999,"edgeCode":3},{"id":101,"adjGrids":[43,54],"minPercent":[10,11],"maxPercent":[1,1],"height":-9999,"edgeCode":0},{"id":102,"adjGrids":[43,null],"minPercent":[3,7],"maxPercent":[4,7],"height":-9999,"edgeCode":3},{"id":103,"adjGrids":[44,55],"minPercent":[0,1],"maxPercent":[1,11],"height":-9999,"edgeCode":0},{"id":104,"adjGrids":[44,null],"minPercent":[4,7],"maxPercent":[5,7],"height":-9999,"edgeCode":1},{"id":105,"adjGrids":[44,45],"minPercent":[4,7],"maxPercent":[5,7],"height":-9999,"edgeCode":3},{"id":106,"adjGrids":[45,56],"minPercent":[1,11],"maxPercent":[2,11],"height":-9999,"edgeCode":0},{"id":107,"adjGrids":[45,46],"minPercent":[4,7],"maxPercent":[5,7],"height":-9999,"edgeCode":3},{"id":108,"adjGrids":[46,57],"minPercent":[2,11],"maxPercent":[3,11],"height":-9999,"edgeCode":0},{"id":109,"adjGrids":[46,47],"minPercent":[4,7],"maxPercent":[5,7],"height":-9999,"edgeCode":3},{"id":110,"adjGrids":[47,58],"minPercent":[3,11],"maxPercent":[4,11],"height":-9999,"edgeCode":0},{"id":111,"adjGrids":[47,48],"minPercent":[4,7],"maxPercent":[5,7],"height":-9999,"edgeCode":3},{"id":112,"adjGrids":[48,59],"minPercent":[4,11],"maxPercent":[5,11],"height":-9999,"edgeCode":0},{"id":113,"adjGrids":[48,49],"minPercent":[4,7],"maxPercent":[5,7],"height":-9999,"edgeCode":3},{"id":114,"adjGrids":[49,60],"minPercent":[5,11],"maxPercent":[6,11],"height":-9999,"edgeCode":0},{"id":115,"adjGrids":[49,50],"minPercent":[4,7],"maxPercent":[5,7],"height":-9999,"edgeCode":3},{"id":116,"adjGrids":[50,61],"minPercent":[6,11],"maxPercent":[7,11],"height":-9999,"edgeCode":0},{"id":117,"adjGrids":[50,51],"minPercent":[4,7],"maxPercent":[5,7],"height":-9999,"edgeCode":3},{"id":118,"adjGrids":[51,62],"minPercent":[7,11],"maxPercent":[8,11],"height":-9999,"edgeCode":0},{"id":119,"adjGrids":[51,52],"minPercent":[4,7],"maxPercent":[5,7],"height":-9999,"edgeCode":3},{"id":120,"adjGrids":[52,63],"minPercent":[8,11],"maxPercent":[9,11],"height":-9999,"edgeCode":0},{"id":121,"adjGrids":[52,53],"minPercent":[4,7],"maxPercent":[5,7],"height":-9999,"edgeCode":3},{"id":122,"adjGrids":[53,64],"minPercent":[9,11],"maxPercent":[10,11],"height":-9999,"edgeCode":0},{"id":123,"adjGrids":[53,54],"minPercent":[4,7],"maxPercent":[5,7],"height":-9999,"edgeCode":3},{"id":124,"adjGrids":[54,65],"minPercent":[10,11],"maxPercent":[1,1],"height":-9999,"edgeCode":0},{"id":125,"adjGrids":[54,null],"minPercent":[4,7],"maxPercent":[5,7],"height":-9999,"edgeCode":3},{"id":126,"adjGrids":[55,66],"minPercent":[0,1],"maxPercent":[1,11],"height":-9999,"edgeCode":0},{"id":127,"adjGrids":[55,null],"minPercent":[5,7],"maxPercent":[6,7],"height":-9999,"edgeCode":1},{"id":128,"adjGrids":[55,56],"minPercent":[5,7],"maxPercent":[6,7],"height":-9999,"edgeCode":3},{"id":129,"adjGrids":[56,67],"minPercent":[1,11],"maxPercent":[2,11],"height":-9999,"edgeCode":0},{"id":130,"adjGrids":[56,57],"minPercent":[5,7],"maxPercent":[6,7],"height":-9999,"edgeCode":3},{"id":131,"adjGrids":[57,68],"minPercent":[2,11],"maxPercent":[3,11],"height":-9999,"edgeCode":0},{"id":132,"adjGrids":[57,58],"minPercent":[5,7],"maxPercent":[6,7],"height":-9999,"edgeCode":3},{"id":133,"adjGrids":[58,69],"minPercent":[3,11],"maxPercent":[4,11],"height":-9999,"edgeCode":0},{"id":134,"adjGrids":[58,59],"minPercent":[5,7],"maxPercent":[6,7],"height":-9999,"edgeCode":3},{"id":135,"adjGrids":[59,70],"minPercent":[4,11],"maxPercent":[5,11],"height":-9999,"edgeCode":0},{"id":136,"adjGrids":[59,60],"minPercent":[5,7],"maxPercent":[6,7],"height":-9999,"edgeCode":3},{"id":137,"adjGrids":[60,71],"minPercent":[5,11],"maxPercent":[6,11],"height":-9999,"edgeCode":0},{"id":138,"adjGrids":[60,61],"minPercent":[5,7],"maxPercent":[6,7],"height":-9999,"edgeCode":3},{"id":139,"adjGrids":[61,72],"minPercent":[6,11],"maxPercent":[7,11],"height":-9999,"edgeCode":0},{"id":140,"adjGrids":[61,62],"minPercent":[5,7],"maxPercent":[6,7],"height":-9999,"edgeCode":3},{"id":141,"adjGrids":[62,73],"minPercent":[7,11],"maxPercent":[8,11],"height":-9999,"edgeCode":0},{"id":142,"adjGrids":[62,63],"minPercent":[5,7],"maxPercent":[6,7],"height":-9999,"edgeCode":3},{"id":143,"adjGrids":[63,74],"minPercent":[8,11],"maxPercent":[9,11],"height":-9999,"edgeCode":0},{"id":144,"adjGrids":[63,64],"minPercent":[5,7],"maxPercent":[6,7],"height":-9999,"edgeCode":3},{"id":145,"adjGrids":[64,75],"minPercent":[9,11],"maxPercent":[10,11],"height":-9999,"edgeCode":0},{"id":146,"adjGrids":[64,65],"minPercent":[5,7],"maxPercent":[6,7],"height":-9999,"edgeCode":3},{"id":147,"adjGrids":[65,76],"minPercent":[10,11],"maxPercent":[1,1],"height":-9999,"edgeCode":0},{"id":148,"adjGrids":[65,null],"minPercent":[5,7],"maxPercent":[6,7],"height":-9999,"edgeCode":3},{"id":149,"adjGrids":[66,null],"minPercent":[0,1],"maxPercent":[1,11],"height":-9999,"edgeCode":0},{"id":150,"adjGrids":[66,null],"minPercent":[6,7],"maxPercent":[1,1],"height":-9999,"edgeCode":1},{"id":151,"adjGrids":[66,67],"minPercent":[6,7],"maxPercent":[1,1],"height":-9999,"edgeCode":3},{"id":152,"adjGrids":[67,null],"minPercent":[1,11],"maxPercent":[2,11],"height":-9999,"edgeCode":0},{"id":153,"adjGrids":[67,68],"minPercent":[6,7],"maxPercent":[1,1],"height":-9999,"edgeCode":3},{"id":154,"adjGrids":[68,null],"minPercent":[2,11],"maxPercent":[3,11],"height":-9999,"edgeCode":0},{"id":155,"adjGrids":[68,69],"minPercent":[6,7],"maxPercent":[1,1],"height":-9999,"edgeCode":3},{"id":156,"adjGrids":[69,null],"minPercent":[3,11],"maxPercent":[4,11],"height":-9999,"edgeCode":0},{"id":157,"adjGrids":[69,70],"minPercent":[6,7],"maxPercent":[1,1],"height":-9999,"edgeCode":3},{"id":158,"adjGrids":[70,null],"minPercent":[4,11],"maxPercent":[5,11],"height":-9999,"edgeCode":0},{"id":159,"adjGrids":[70,71],"minPercent":[6,7],"maxPercent":[1,1],"height":-9999,"edgeCode":3},{"id":160,"adjGrids":[71,null],"minPercent":[5,11],"maxPercent":[6,11],"height":-9999,"edgeCode":0},{"id":161,"adjGrids":[71,72],"minPercent":[6,7],"maxPercent":[1,1],"height":-9999,"edgeCode":3},{"id":162,"adjGrids":[72,null],"minPercent":[6,11],"maxPercent":[7,11],"height":-9999,"edgeCode":0},{"id":163,"adjGrids":[72,73],"minPercent":[6,7],"maxPercent":[1,1],"height":-9999,"edgeCode":3},{"id":164,"adjGrids":[73,null],"minPercent":[7,11],"maxPercent":[8,11],"height":-9999,"edgeCode":0},{"id":165,"adjGrids":[73,74],"minPercent":[6,7],"maxPercent":[1,1],"height":-9999,"edgeCode":3},{"id":166,"adjGrids":[74,null],"minPercent":[8,11],"maxPercent":[9,11],"height":-9999,"edgeCode":0},{"id":167,"adjGrids":[74,75],"minPercent":[6,7],"maxPercent":[1,1],"height":-9999,"edgeCode":3},{"id":168,"adjGrids":[75,null],"minPercent":[9,11],"maxPercent":[10,11],"height":-9999,"edgeCode":0},{"id":169,"adjGrids":[75,76],"minPercent":[6,7],"maxPercent":[1,1],"height":-9999,"edgeCode":3},{"id":170,"adjGrids":[76,null],"minPercent":[10,11],"maxPercent":[1,1],"height":-9999,"edgeCode":0},{"id":171,"adjGrids":[76,null],"minPercent":[6,7],"maxPercent":[1,1],"height":-9999,"edgeCode":3}]}